django_filter_ex-1.2.0.dist-info/LICENSE.txt
django_filter_ex-1.2.0.dist-info/METADATA
django_filter_ex-1.2.0.dist-info/RECORD
django_filter_ex-1.2.0.dist-info/WHEEL
django_filter_ex-1.2.0.dist-info/top_level.txt
django_filters/__init__.py
django_filters/compat.py
django_filters/conf.py
django_filters/constants.py
django_filters/exceptions.py
django_filters/fields.py
django_filters/filters.py
django_filters/filterset.py
django_filters/models.py
django_filters/utils.py
django_filters/views.py
django_filters/widgets.py
django_filters/locale/de/LC_MESSAGES/django.mo
django_filters/locale/de/LC_MESSAGES/django.po
django_filters/locale/es_AR/LC_MESSAGES/django.mo
django_filters/locale/es_AR/LC_MESSAGES/django.po
django_filters/locale/es_ES/LC_MESSAGES/django.mo
django_filters/locale/es_ES/LC_MESSAGES/django.po
django_filters/locale/fr/LC_MESSAGES/django.mo
django_filters/locale/fr/LC_MESSAGES/django.po
django_filters/locale/pl/LC_MESSAGES/django.mo
django_filters/locale/pl/LC_MESSAGES/django.po
django_filters/locale/ru/LC_MESSAGES/django.mo
django_filters/locale/ru/LC_MESSAGES/django.po
django_filters/locale/zh_CN/LC_MESSAGES/django.po
django_filters/rest_framework/__init__.py
django_filters/rest_framework/backends.py
django_filters/rest_framework/filters.py
django_filters/rest_framework/filterset.py
django_filters/templates/django_filters/rest_framework/crispy_form.html
django_filters/templates/django_filters/rest_framework/form.html
django_filters/templates/django_filters/widgets/multiwidget.html
