Metadata-Version: 1.2
Name: django-filter-ex
Version: 1.2.0
Summary: Django-filter is a reusable Django application for allowing users to filter querysets dynamically.
Home-page: https://github.com/tikal.tech/django-filter/tree/py2-compat
Author: Alex Gaynor
Author-email: alex.gaynor@gmail.com
Maintainer: Tikal Tech
Maintainer-email: bruno@tikal.tech
License: BSD
Platform: UNKNOWN
Classifier: Development Status :: 5 - Production/Stable
Classifier: Environment :: Web Environment
Classifier: Intended Audience :: Developers
Classifier: License :: OSI Approved :: BSD License
Classifier: Operating System :: OS Independent
Classifier: Framework :: Django
Classifier: Framework :: Django :: 1.11
Classifier: Programming Language :: Python
Classifier: Programming Language :: Python :: 2
Classifier: Programming Language :: Python :: 2.7
Classifier: Programming Language :: Python :: 3
Classifier: Programming Language :: Python :: 3.6
Classifier: Framework :: Django
